setup.py
colormod/__init__.py
colormod.egg-info/PKG-INFO
colormod.egg-info/SOURCES.txt
colormod.egg-info/dependency_links.txt
colormod.egg-info/top_level.txt