Metadata-Version: 1.1
Name: colormod
Version: 1.0.1
Summary: Makes the use of ANSI colors much easier. Its just a simplified version of colorama.Fore
Home-page: UNKNOWN
Author: LiquidDevect
Author-email: UNKNOWN
License: Do whatever you want
Keywords: colors
Platform: UNKNOWN
Requires: colorama
